<funkload version="1.16.1" time="2014-12-05T13:45:49.145611">
<config key="sleep_time_min" value="0.0" />
<config key="node" value="169-231-98-160.wireless.ucsb.edu" />
<config key="startup_delay" value="0.01" />
<config key="cycles" value="[1]" />
<config key="cycle_time" value="1.0" />
<config key="description" value="No test description" />
<config key="configuration_file" value="/Users/steffenfb/programming/xup/loadtestingsteffen/Critical.conf" />
<config key="class_title" value="Critical Path FunkLoad tests" />
<config key="server_url" value="http://localhost:3000" />
<config key="module" value="test_Critical" />
<config key="id" value="join_all_parties" />
<config key="class_description" value="Testing the critical path of the lab app" />
<config key="sleep_time" value="0.01" />
<config key="sleep_time_max" value="0.5" />
<config key="duration" value="10" />
<config key="method" value="join_all_parties" />
<config key="log_xml" value="/Users/steffenfb/programming/xup/loadtestingsteffen/localcritical-bench.xml" />
<config key="class" value="Critical" />
<config key="python_version" value="2.7.5" />
<response cycle="000" cvus="001" thread="000" suite="Critical" name="join_all_parties" step="001" number="001" type="get" result="Successful" url="" code="200" description="Get root URL" time="1417815949.15" duration="0.147462844849" />
<response cycle="000" cvus="001" thread="000" suite="Critical" name="join_all_parties" step="001" number="002" type="link" result="Successful" url="/bootstrap/3.2.0/css/bootstrap.min.css" code="200" description="" time="1417815949.29" duration="0.53187084198" />
<response cycle="000" cvus="001" thread="000" suite="Critical" name="join_all_parties" step="001" number="003" type="link" result="Successful" url="/assets/bootstrap_and_customization.css?body=1" code="200" description="" time="1417815949.83" duration="0.00727486610413" />
<response cycle="000" cvus="001" thread="000" suite="Critical" name="join_all_parties" step="001" number="004" type="link" result="Successful" url="/assets/join_members.css?body=1" code="200" description="" time="1417815949.83" duration="0.00529003143311" />
<response cycle="000" cvus="001" thread="000" suite="Critical" name="join_all_parties" step="001" number="005" type="link" result="Successful" url="/assets/parties.css?body=1" code="200" description="" time="1417815949.84" duration="0.00487494468689" />
<response cycle="000" cvus="001" thread="000" suite="Critical" name="join_all_parties" step="001" number="006" type="link" result="Successful" url="/assets/profiles.css?body=1" code="200" description="" time="1417815949.84" duration="0.00496602058411" />
<response cycle="000" cvus="001" thread="000" suite="Critical" name="join_all_parties" step="001" number="007" type="link" result="Successful" url="/assets/scaffolds.css?body=1" code="200" description="" time="1417815949.85" duration="0.00509810447693" />
<response cycle="000" cvus="001" thread="000" suite="Critical" name="join_all_parties" step="001" number="008" type="link" result="Successful" url="/assets/application.css?body=1" code="200" description="" time="1417815949.86" duration="0.00565600395203" />
<response cycle="000" cvus="001" thread="000" suite="Critical" name="join_all_parties" step="001" number="009" type="link" result="Successful" url="/assets/bootstrap-datetimepicker.css?body=1" code="200" description="" time="1417815949.86" duration="0.0051121711731" />
<response cycle="000" cvus="001" thread="000" suite="Critical" name="join_all_parties" step="001" number="010" type="image" result="Successful" url="/2013/05/img_1380.jpg" code="200" description="" time="1417815949.87" duration="4.366314888" />
<response cycle="000" cvus="001" thread="000" suite="Critical" name="join_all_parties" step="001" number="011" type="image" result="Successful" url="/2014/04/maxresdefault.jpg" code="200" description="" time="1417815954.24" duration="0.223169088364" />
<response cycle="000" cvus="001" thread="000" suite="Critical" name="join_all_parties" step="001" number="012" type="image" result="Successful" url="/_-tDuDhxev0k/TLKuMBwh6sI/AAAAAAAAACc/hjNcFNVbBEI/s1600/IMG_0091-1.jpg" code="200" description="" time="1417815954.46" duration="0.188219070435" />
<response cycle="000" cvus="001" thread="000" suite="Critical" name="join_all_parties" step="001" number="013" type="image" result="Successful" url="/img/photos/2009/04/08/P4040977_t479.jpg?6626f76dcd72edc2e28f46812c7026450162bdb2" code="200" description="" time="1417815954.65" duration="0.419037818909" />
<response cycle="000" cvus="001" thread="000" suite="Critical" name="join_all_parties" step="001" number="014" type="image" result="Successful" url="/rapgenius/beer_pong1.jpg" code="200" description="" time="1417815955.07" duration="1.31147098541" />
<response cycle="000" cvus="001" thread="000" suite="Critical" name="join_all_parties" step="001" number="015" type="image" result="Successful" url="/images/drink.19_1.jpg" code="200" description="" time="1417815956.38" duration="0.705830097198" />
<response cycle="000" cvus="001" thread="000" suite="Critical" name="join_all_parties" step="002" number="001" type="get" result="Successful" url="/users/sign_up" code="200" description="View the user signup page" time="1417815957.46" duration="0.0989849567413" />
<response cycle="000" cvus="001" thread="000" suite="Critical" name="join_all_parties" step="003" number="001" type="post" result="Successful" url="/users" code="302" description="Create New User" time="1417815957.6" duration="0.155333042145" />
<response cycle="000" cvus="001" thread="000" suite="Critical" name="join_all_parties" step="003" number="002" type="get" result="Successful" url="/profiles/3" code="200" description="" time="1417815957.76" duration="0.0946028232574" />
<response cycle="000" cvus="001" thread="000" suite="Critical" name="join_all_parties" step="004" number="001" type="get" result="Successful" url="/index" code="200" description="watching parties to join" time="1417815957.91" duration="0.139112949371" />
<response cycle="000" cvus="001" thread="000" suite="Critical" name="join_all_parties" step="005" number="001" type="post" result="Failure" url="/join_members" code="422" description="Joining party" time="1417815958.38" duration="0.0364670753479">
  <headers>
    <header name="content-length" value="16362" />
    <header name="connection" value="close" />
    <header name="x-request-id" value="adb285b2-e66f-445f-995d-f8cad0a7e9de" />
    <header name="server" value="WEBrick/1.3.1 (Ruby/2.0.0/2014-05-08)" />
    <header name="x-runtime" value="0.031840" />
    <header name="date" value="Fri, 05 Dec 2014 21:45:58 GMT" />
    <header name="content-type" value="text/html; charset=utf-8" />
  </headers>
  <body><![CDATA[
<!DOCTYPE html>
<html lang="en">
<head>
  <meta charset="utf-8" />
  <title>Action Controller: Exception caught</title>
  <style>
    body {
      background-color: #FAFAFA;
      color: #333;
      margin: 0px;
    }

    body, p, ol, ul, td {
      font-family: helvetica, verdana, arial, sans-serif;
      font-size:   13px;
      line-height: 18px;
    }

    pre {
      font-size: 11px;
      white-space: pre-wrap;
    }

    pre.box {
      border: 1px solid #EEE;
      padding: 10px;
      margin: 0px;
      width: 958px;
    }

    header {
      color: #F0F0F0;
      background: #C52F24;
      padding: 0.5em 1.5em;
    }

    h1 {
      margin: 0.2em 0;
      line-height: 1.1em;
      font-size: 2em;
    }

    h2 {
      color: #C52F24;
      line-height: 25px;
    }

    .details {
      border: 1px solid #D0D0D0;
      border-radius: 4px;
      margin: 1em 0px;
      display: block;
      width: 978px;
    }

    .summary {
      padding: 8px 15px;
      border-bottom: 1px solid #D0D0D0;
      display: block;
    }

    .details pre {
      margin: 5px;
      border: none;
    }

    #container {
      box-sizing: border-box;
      width: 100%;
      padding: 0 1.5em;
    }

    .source * {
      margin: 0px;
      padding: 0px;
    }

    .source {
      border: 1px solid #D9D9D9;
      background: #ECECEC;
      width: 978px;
    }

    .source pre {
      padding: 10px 0px;
      border: none;
    }

    .source .data {
      font-size: 80%;
      overflow: auto;
      background-color: #FFF;
    }

    .info {
      padding: 0.5em;
    }

    .source .data .line_numbers {
      background-color: #ECECEC;
      color: #AAA;
      padding: 1em .5em;
      border-right: 1px solid #DDD;
      text-align: right;
    }

    .line {
      padding-left: 10px;
    }

    .line:hover {
      background-color: #F6F6F6;
    }

    .line.active {
      background-color: #FFCCCC;
    }

    a { color: #980905; }
    a:visited { color: #666; }
    a:hover { color: #C52F24; }

    
  </style>

  <script>
    var toggle = function(id) {
      var s = document.getElementById(id).style;
      s.display = s.display == 'none' ? 'block' : 'none';
      return false;
    }
    var show = function(id) {
      document.getElementById(id).style.display = 'block';
    }
    var hide = function(id) {
      document.getElementById(id).style.display = 'none';
    }
    var toggleTrace = function() {
      return toggle('blame_trace');
    }
    var toggleSessionDump = function() {
      return toggle('session_dump');
    }
    var toggleEnvDump = function() {
      return toggle('env_dump');
    }
  </script>
</head>
<body>

<header>
  <h1>
    ActionController::InvalidAuthenticityToken
      in JoinMembersController#create
  </h1>
</header>

<div id="container">
  <h2>ActionController::InvalidAuthenticityToken</h2>

  
  
<p><code>Rails.root: /Users/steffenfb/programming/xup</code></p>

<div id="traces">
    <a href="#" onclick="hide(&#39;Framework-Trace&#39;);hide(&#39;Full-Trace&#39;);show(&#39;Application-Trace&#39;);; return false;">Application Trace</a> |
    <a href="#" onclick="hide(&#39;Application-Trace&#39;);hide(&#39;Full-Trace&#39;);show(&#39;Framework-Trace&#39;);; return false;">Framework Trace</a> |
    <a href="#" onclick="hide(&#39;Application-Trace&#39;);hide(&#39;Framework-Trace&#39;);show(&#39;Full-Trace&#39;);; return false;">Full Trace</a> 

    <div id="Application-Trace" style="display: block;">
      <pre><code></code></pre>
    </div>
    <div id="Framework-Trace" style="display: none;">
      <pre><code>actionpack (4.1.6) lib/action_controller/metal/request_forgery_protection.rb:176:in `handle_unverified_request&#39;
actionpack (4.1.6) lib/action_controller/metal/request_forgery_protection.rb:202:in `handle_unverified_request&#39;
devise (3.4.1) lib/devise/controllers/helpers.rb:251:in `handle_unverified_request&#39;
actionpack (4.1.6) lib/action_controller/metal/request_forgery_protection.rb:197:in `verify_authenticity_token&#39;
activesupport (4.1.6) lib/active_support/callbacks.rb:424:in `block in make_lambda&#39;
activesupport (4.1.6) lib/active_support/callbacks.rb:160:in `call&#39;
activesupport (4.1.6) lib/active_support/callbacks.rb:160:in `block in halting&#39;
activesupport (4.1.6) lib/active_support/callbacks.rb:86:in `call&#39;
activesupport (4.1.6) lib/active_support/callbacks.rb:86:in `run_callbacks&#39;
actionpack (4.1.6) lib/abstract_controller/callbacks.rb:19:in `process_action&#39;
actionpack (4.1.6) lib/action_controller/metal/rescue.rb:29:in `process_action&#39;
actionpack (4.1.6) lib/action_controller/metal/instrumentation.rb:31:in `block in process_action&#39;
activesupport (4.1.6) lib/active_support/notifications.rb:159:in `block in instrument&#39;
activesupport (4.1.6) lib/active_support/notifications/instrumenter.rb:20:in `instrument&#39;
activesupport (4.1.6) lib/active_support/notifications.rb:159:in `instrument&#39;
actionpack (4.1.6) lib/action_controller/metal/instrumentation.rb:30:in `process_action&#39;
actionpack (4.1.6) lib/action_controller/metal/params_wrapper.rb:250:in `process_action&#39;
activerecord (4.1.6) lib/active_record/railties/controller_runtime.rb:18:in `process_action&#39;
actionpack (4.1.6) lib/abstract_controller/base.rb:136:in `process&#39;
actionview (4.1.6) lib/action_view/rendering.rb:30:in `process&#39;
actionpack (4.1.6) lib/action_controller/metal.rb:196:in `dispatch&#39;
actionpack (4.1.6) lib/action_controller/metal/rack_delegation.rb:13:in `dispatch&#39;
actionpack (4.1.6) lib/action_controller/metal.rb:232:in `block in action&#39;
actionpack (4.1.6) lib/action_dispatch/routing/route_set.rb:82:in `call&#39;
actionpack (4.1.6) lib/action_dispatch/routing/route_set.rb:82:in `dispatch&#39;
actionpack (4.1.6) lib/action_dispatch/routing/route_set.rb:50:in `call&#39;
actionpack (4.1.6) lib/action_dispatch/journey/router.rb:73:in `block in call&#39;
actionpack (4.1.6) lib/action_dispatch/journey/router.rb:59:in `each&#39;
actionpack (4.1.6) lib/action_dispatch/journey/router.rb:59:in `call&#39;
actionpack (4.1.6) lib/action_dispatch/routing/route_set.rb:678:in `call&#39;
omniauth (1.2.2) lib/omniauth/strategy.rb:186:in `call!&#39;
omniauth (1.2.2) lib/omniauth/strategy.rb:164:in `call&#39;
warden (1.2.3) lib/warden/manager.rb:35:in `block in call&#39;
warden (1.2.3) lib/warden/manager.rb:34:in `catch&#39;
warden (1.2.3) lib/warden/manager.rb:34:in `call&#39;
rack (1.5.2) lib/rack/etag.rb:23:in `call&#39;
rack (1.5.2) lib/rack/conditionalget.rb:35:in `call&#39;
rack (1.5.2) lib/rack/head.rb:11:in `call&#39;
actionpack (4.1.6) lib/action_dispatch/middleware/params_parser.rb:27:in `call&#39;
actionpack (4.1.6) lib/action_dispatch/middleware/flash.rb:254:in `call&#39;
rack (1.5.2) lib/rack/session/abstract/id.rb:225:in `context&#39;
rack (1.5.2) lib/rack/session/abstract/id.rb:220:in `call&#39;
actionpack (4.1.6) lib/action_dispatch/middleware/cookies.rb:560:in `call&#39;
activerecord (4.1.6) lib/active_record/query_cache.rb:36:in `call&#39;
activerecord (4.1.6) lib/active_record/connection_adapters/abstract/connection_pool.rb:621:in `call&#39;
activerecord (4.1.6) lib/active_record/migration.rb:380:in `call&#39;
actionpack (4.1.6) lib/action_dispatch/middleware/callbacks.rb:29:in `block in call&#39;
activesupport (4.1.6) lib/active_support/callbacks.rb:82:in `run_callbacks&#39;
actionpack (4.1.6) lib/action_dispatch/middleware/callbacks.rb:27:in `call&#39;
actionpack (4.1.6) lib/action_dispatch/middleware/reloader.rb:73:in `call&#39;
actionpack (4.1.6) lib/action_dispatch/middleware/remote_ip.rb:76:in `call&#39;
actionpack (4.1.6) lib/action_dispatch/middleware/debug_exceptions.rb:17:in `call&#39;
actionpack (4.1.6) lib/action_dispatch/middleware/show_exceptions.rb:30:in `call&#39;
railties (4.1.6) lib/rails/rack/logger.rb:38:in `call_app&#39;
railties (4.1.6) lib/rails/rack/logger.rb:20:in `block in call&#39;
activesupport (4.1.6) lib/active_support/tagged_logging.rb:68:in `block in tagged&#39;
activesupport (4.1.6) lib/active_support/tagged_logging.rb:26:in `tagged&#39;
activesupport (4.1.6) lib/active_support/tagged_logging.rb:68:in `tagged&#39;
railties (4.1.6) lib/rails/rack/logger.rb:20:in `call&#39;
request_store (1.1.0) lib/request_store/middleware.rb:8:in `call&#39;
actionpack (4.1.6) lib/action_dispatch/middleware/request_id.rb:21:in `call&#39;
rack (1.5.2) lib/rack/methodoverride.rb:21:in `call&#39;
rack (1.5.2) lib/rack/runtime.rb:17:in `call&#39;
activesupport (4.1.6) lib/active_support/cache/strategy/local_cache_middleware.rb:26:in `call&#39;
rack (1.5.2) lib/rack/lock.rb:17:in `call&#39;
actionpack (4.1.6) lib/action_dispatch/middleware/static.rb:64:in `call&#39;
rack (1.5.2) lib/rack/sendfile.rb:112:in `call&#39;
railties (4.1.6) lib/rails/engine.rb:514:in `call&#39;
railties (4.1.6) lib/rails/application.rb:144:in `call&#39;
rack (1.5.2) lib/rack/lock.rb:17:in `call&#39;
rack (1.5.2) lib/rack/content_length.rb:14:in `call&#39;
rack (1.5.2) lib/rack/handler/webrick.rb:60:in `service&#39;
/System/Library/Frameworks/Ruby.framework/Versions/2.0/usr/lib/ruby/2.0.0/webrick/httpserver.rb:138:in `service&#39;
/System/Library/Frameworks/Ruby.framework/Versions/2.0/usr/lib/ruby/2.0.0/webrick/httpserver.rb:94:in `run&#39;
/System/Library/Frameworks/Ruby.framework/Versions/2.0/usr/lib/ruby/2.0.0/webrick/server.rb:295:in `block in start_thread&#39;</code></pre>
    </div>
    <div id="Full-Trace" style="display: none;">
      <pre><code>actionpack (4.1.6) lib/action_controller/metal/request_forgery_protection.rb:176:in `handle_unverified_request&#39;
actionpack (4.1.6) lib/action_controller/metal/request_forgery_protection.rb:202:in `handle_unverified_request&#39;
devise (3.4.1) lib/devise/controllers/helpers.rb:251:in `handle_unverified_request&#39;
actionpack (4.1.6) lib/action_controller/metal/request_forgery_protection.rb:197:in `verify_authenticity_token&#39;
activesupport (4.1.6) lib/active_support/callbacks.rb:424:in `block in make_lambda&#39;
activesupport (4.1.6) lib/active_support/callbacks.rb:160:in `call&#39;
activesupport (4.1.6) lib/active_support/callbacks.rb:160:in `block in halting&#39;
activesupport (4.1.6) lib/active_support/callbacks.rb:86:in `call&#39;
activesupport (4.1.6) lib/active_support/callbacks.rb:86:in `run_callbacks&#39;
actionpack (4.1.6) lib/abstract_controller/callbacks.rb:19:in `process_action&#39;
actionpack (4.1.6) lib/action_controller/metal/rescue.rb:29:in `process_action&#39;
actionpack (4.1.6) lib/action_controller/metal/instrumentation.rb:31:in `block in process_action&#39;
activesupport (4.1.6) lib/active_support/notifications.rb:159:in `block in instrument&#39;
activesupport (4.1.6) lib/active_support/notifications/instrumenter.rb:20:in `instrument&#39;
activesupport (4.1.6) lib/active_support/notifications.rb:159:in `instrument&#39;
actionpack (4.1.6) lib/action_controller/metal/instrumentation.rb:30:in `process_action&#39;
actionpack (4.1.6) lib/action_controller/metal/params_wrapper.rb:250:in `process_action&#39;
activerecord (4.1.6) lib/active_record/railties/controller_runtime.rb:18:in `process_action&#39;
actionpack (4.1.6) lib/abstract_controller/base.rb:136:in `process&#39;
actionview (4.1.6) lib/action_view/rendering.rb:30:in `process&#39;
actionpack (4.1.6) lib/action_controller/metal.rb:196:in `dispatch&#39;
actionpack (4.1.6) lib/action_controller/metal/rack_delegation.rb:13:in `dispatch&#39;
actionpack (4.1.6) lib/action_controller/metal.rb:232:in `block in action&#39;
actionpack (4.1.6) lib/action_dispatch/routing/route_set.rb:82:in `call&#39;
actionpack (4.1.6) lib/action_dispatch/routing/route_set.rb:82:in `dispatch&#39;
actionpack (4.1.6) lib/action_dispatch/routing/route_set.rb:50:in `call&#39;
actionpack (4.1.6) lib/action_dispatch/journey/router.rb:73:in `block in call&#39;
actionpack (4.1.6) lib/action_dispatch/journey/router.rb:59:in `each&#39;
actionpack (4.1.6) lib/action_dispatch/journey/router.rb:59:in `call&#39;
actionpack (4.1.6) lib/action_dispatch/routing/route_set.rb:678:in `call&#39;
omniauth (1.2.2) lib/omniauth/strategy.rb:186:in `call!&#39;
omniauth (1.2.2) lib/omniauth/strategy.rb:164:in `call&#39;
warden (1.2.3) lib/warden/manager.rb:35:in `block in call&#39;
warden (1.2.3) lib/warden/manager.rb:34:in `catch&#39;
warden (1.2.3) lib/warden/manager.rb:34:in `call&#39;
rack (1.5.2) lib/rack/etag.rb:23:in `call&#39;
rack (1.5.2) lib/rack/conditionalget.rb:35:in `call&#39;
rack (1.5.2) lib/rack/head.rb:11:in `call&#39;
actionpack (4.1.6) lib/action_dispatch/middleware/params_parser.rb:27:in `call&#39;
actionpack (4.1.6) lib/action_dispatch/middleware/flash.rb:254:in `call&#39;
rack (1.5.2) lib/rack/session/abstract/id.rb:225:in `context&#39;
rack (1.5.2) lib/rack/session/abstract/id.rb:220:in `call&#39;
actionpack (4.1.6) lib/action_dispatch/middleware/cookies.rb:560:in `call&#39;
activerecord (4.1.6) lib/active_record/query_cache.rb:36:in `call&#39;
activerecord (4.1.6) lib/active_record/connection_adapters/abstract/connection_pool.rb:621:in `call&#39;
activerecord (4.1.6) lib/active_record/migration.rb:380:in `call&#39;
actionpack (4.1.6) lib/action_dispatch/middleware/callbacks.rb:29:in `block in call&#39;
activesupport (4.1.6) lib/active_support/callbacks.rb:82:in `run_callbacks&#39;
actionpack (4.1.6) lib/action_dispatch/middleware/callbacks.rb:27:in `call&#39;
actionpack (4.1.6) lib/action_dispatch/middleware/reloader.rb:73:in `call&#39;
actionpack (4.1.6) lib/action_dispatch/middleware/remote_ip.rb:76:in `call&#39;
actionpack (4.1.6) lib/action_dispatch/middleware/debug_exceptions.rb:17:in `call&#39;
actionpack (4.1.6) lib/action_dispatch/middleware/show_exceptions.rb:30:in `call&#39;
railties (4.1.6) lib/rails/rack/logger.rb:38:in `call_app&#39;
railties (4.1.6) lib/rails/rack/logger.rb:20:in `block in call&#39;
activesupport (4.1.6) lib/active_support/tagged_logging.rb:68:in `block in tagged&#39;
activesupport (4.1.6) lib/active_support/tagged_logging.rb:26:in `tagged&#39;
activesupport (4.1.6) lib/active_support/tagged_logging.rb:68:in `tagged&#39;
railties (4.1.6) lib/rails/rack/logger.rb:20:in `call&#39;
request_store (1.1.0) lib/request_store/middleware.rb:8:in `call&#39;
actionpack (4.1.6) lib/action_dispatch/middleware/request_id.rb:21:in `call&#39;
rack (1.5.2) lib/rack/methodoverride.rb:21:in `call&#39;
rack (1.5.2) lib/rack/runtime.rb:17:in `call&#39;
activesupport (4.1.6) lib/active_support/cache/strategy/local_cache_middleware.rb:26:in `call&#39;
rack (1.5.2) lib/rack/lock.rb:17:in `call&#39;
actionpack (4.1.6) lib/action_dispatch/middleware/static.rb:64:in `call&#39;
rack (1.5.2) lib/rack/sendfile.rb:112:in `call&#39;
railties (4.1.6) lib/rails/engine.rb:514:in `call&#39;
railties (4.1.6) lib/rails/application.rb:144:in `call&#39;
rack (1.5.2) lib/rack/lock.rb:17:in `call&#39;
rack (1.5.2) lib/rack/content_length.rb:14:in `call&#39;
rack (1.5.2) lib/rack/handler/webrick.rb:60:in `service&#39;
/System/Library/Frameworks/Ruby.framework/Versions/2.0/usr/lib/ruby/2.0.0/webrick/httpserver.rb:138:in `service&#39;
/System/Library/Frameworks/Ruby.framework/Versions/2.0/usr/lib/ruby/2.0.0/webrick/httpserver.rb:94:in `run&#39;
/System/Library/Frameworks/Ruby.framework/Versions/2.0/usr/lib/ruby/2.0.0/webrick/server.rb:295:in `block in start_thread&#39;</code></pre>
    </div>
</div>

  

<h2 style="margin-top: 30px">Request</h2>
<p><b>Parameters</b>:</p> <pre>{&quot;party_id&quot;=&gt;&quot;1&quot;,
 &quot;user_id&quot;=&gt;&quot;3&quot;}</pre>

<div class="details">
  <div class="summary"><a href="#" onclick="return toggleSessionDump()">Toggle session dump</a></div>
  <div id="session_dump" style="display:none"><pre>_csrf_token: &quot;PYfwKms0NrRv38kpowezk5cdfUgP+xpujAsYPN3sjyU=&quot;
session_id: &quot;9ead313975553f81a8f23e219e013eaa&quot;
warden.user.user.key: [[3], &quot;$2a$10$Dc/BJ91ZrKT5wwwdUeiFyu&quot;]</pre></div>
</div>

<div class="details">
  <div class="summary"><a href="#" onclick="return toggleEnvDump()">Toggle env dump</a></div>
  <div id="env_dump" style="display:none"><pre>GATEWAY_INTERFACE: &quot;CGI/1.1&quot;
REMOTE_ADDR: &quot;127.0.0.1&quot;
REMOTE_HOST: &quot;127.0.0.1&quot;
SERVER_NAME: &quot;localhost&quot;
SERVER_PROTOCOL: &quot;HTTP/1.1&quot;</pre></div>
</div>

<h2 style="margin-top: 30px">Response</h2>
<p><b>Headers</b>:</p> <pre>None</pre>

</div>


</body>
</html>

]]>
  </body>
</response>
<testResult cycle="000" cvus="001" thread="000" suite="Critical" name="join_all_parties"  time="1417815949.15" result="Failure" steps="5" duration="9.27018713951" connection_duration="8.45614862442" requests="20" pages="4" xmlrpc="0" redirects="1" images="6" links="8" traceback='Traceback (most recent call last):&#10;   File "/Users/steffenfb/programming/loadtest/lib/python2.7/site-packages/funkload/FunkLoadTestCase.py", line 946, in __call__&#10;    testMethod()&#10;   File "/Users/steffenfb/programming/xup/loadtestingsteffen/test_Critical.py", line 49, in join_all_parties&#10;    description="Joining party")&#10;   File "/Users/steffenfb/programming/loadtest/lib/python2.7/site-packages/funkload/FunkLoadTestCase.py", line 383, in post&#10;    method="post", load_auto_links=load_auto_links)&#10;   File "/Users/steffenfb/programming/loadtest/lib/python2.7/site-packages/funkload/FunkLoadTestCase.py", line 299, in _browse&#10;    response = self._connect(url, params, ok_codes, method, description)&#10;   File "/Users/steffenfb/programming/loadtest/lib/python2.7/site-packages/funkload/FunkLoadTestCase.py", line 216, in _connect&#10;    raise self.failureException, str(value.response)&#10; AssertionError: /join_members&#10;HTTP Response 422: Unprocessable Entity&#10;' />
<response cycle="000" cvus="001" thread="000" suite="Critical" name="join_all_parties" step="001" number="001" type="get" result="Successful" url="" code="200" description="Get root URL" time="1417815958.43" duration="0.151485919952" />
<response cycle="000" cvus="001" thread="000" suite="Critical" name="join_all_parties" step="001" number="002" type="link" result="Successful" url="/bootstrap/3.2.0/css/bootstrap.min.css" code="200" description="" time="1417815958.58" duration="0.51656794548" />
<response cycle="000" cvus="001" thread="000" suite="Critical" name="join_all_parties" step="001" number="003" type="link" result="Successful" url="/assets/bootstrap_and_customization.css?body=1" code="200" description="" time="1417815959.1" duration="0.00694894790649" />
<response cycle="000" cvus="001" thread="000" suite="Critical" name="join_all_parties" step="001" number="004" type="link" result="Successful" url="/assets/join_members.css?body=1" code="200" description="" time="1417815959.1" duration="0.00535988807678" />
<response cycle="000" cvus="001" thread="000" suite="Critical" name="join_all_parties" step="001" number="005" type="link" result="Successful" url="/assets/parties.css?body=1" code="200" description="" time="1417815959.11" duration="0.00496816635132" />
<response cycle="000" cvus="001" thread="000" suite="Critical" name="join_all_parties" step="001" number="006" type="link" result="Successful" url="/assets/profiles.css?body=1" code="200" description="" time="1417815959.11" duration="0.00493192672729" />
<response cycle="000" cvus="001" thread="000" suite="Critical" name="join_all_parties" step="001" number="007" type="link" result="Successful" url="/assets/scaffolds.css?body=1" code="200" description="" time="1417815959.12" duration="0.00497984886169" />
<response cycle="000" cvus="001" thread="000" suite="Critical" name="join_all_parties" step="001" number="008" type="link" result="Successful" url="/assets/application.css?body=1" code="200" description="" time="1417815959.12" duration="0.00545406341553" />
<response cycle="000" cvus="001" thread="000" suite="Critical" name="join_all_parties" step="001" number="009" type="link" result="Successful" url="/assets/bootstrap-datetimepicker.css?body=1" code="200" description="" time="1417815959.13" duration="0.00508284568787" />
</funkload>
